edpmt/__init__.py
edpmt/cli.py
edpmt/hardware.py
edpmt/transparent.py
edpmt/utils.py
edpmt/web_ui.py
edpmt/hardware/__init__.py
edpmt/hardware/factory.py
edpmt/hardware/gpio_rpi.py
edpmt/hardware/gpio_simulator.py
edpmt/hardware/i2c_simulator.py
edpmt/hardware/i2c_smbus.py
edpmt/hardware/interfaces.py
edpmt/hardware/spi_simulator.py
edpmt/hardware/spi_spidev.py
edpmt/hardware/uart_serial.py
edpmt/hardware/uart_simulator.py
edpmt/hardware/usb_pyusb.py
edpmt/hardware/usb_simulator.py
edpmt-1.0.7.dist-info/licenses/LICENSE
edpmt-1.0.7.dist-info/METADATA
edpmt-1.0.7.dist-info/WHEEL
edpmt-1.0.7.dist-info/entry_points.txt
edpmt-1.0.7.dist-info/top_level.txt
edpmt-1.0.7.dist-info/RECORD
