Metadata-Version: 2.4
Name: edpmt
Version: 1.0.7
Summary: EDPM Transparent - Simple, Secure, Universal Hardware Communication
Home-page: https://github.com/stream-ware/edpmt
Author: Tom Sapletta
Author-email: info@softreck.dev
Project-URL: Bug Reports, https://github.com/stream-ware/edpmt/issues
Project-URL: Source, https://github.com/stream-ware/edpmt
Project-URL: Documentation, https://github.com/stream-ware/edpmt/blob/main/README.md
Keywords: hardware gpio i2c spi uart raspberry-pi iot embedded automation transparent secure
Classifier: Development Status :: 5 - Production/Stable
Classifier: Intended Audience :: Developers
Classifier: Intended Audience :: Science/Research
Classifier: License :: OSI Approved :: Apache Software License
Classifier: Operating System :: OS Independent
Classifier: Programming Language :: Python :: 3
Classifier: Programming Language :: Python :: 3.8
Classifier: Programming Language :: Python :: 3.9
Classifier: Programming Language :: Python :: 3.10
Classifier: Programming Language :: Python :: 3.11
Classifier: Programming Language :: Python :: 3.12
Classifier: Topic :: Scientific/Engineering
Classifier: Topic :: System :: Hardware
Classifier: Topic :: Software Development :: Libraries :: Python Modules
Classifier: Topic :: Internet :: WWW/HTTP :: HTTP Servers
Classifier: Topic :: Communications
Requires-Python: >=3.8
License-File: LICENSE
Requires-Dist: aiohttp>=3.8.0
Requires-Dist: aiohttp-cors>=0.7.0
Requires-Dist: cryptography>=3.4.8
Requires-Dist: websockets>=10.0
Requires-Dist: flask>=2.3.0
Requires-Dist: flask-socketio>=5.3.0
Requires-Dist: portkeeper>=0.1.0
Provides-Extra: dev
Requires-Dist: pytest>=6.0; extra == "dev"
Requires-Dist: pytest-asyncio>=0.18.0; extra == "dev"
Requires-Dist: pytest-cov>=3.0.0; extra == "dev"
Requires-Dist: black>=22.0.0; extra == "dev"
Requires-Dist: flake8>=4.0.0; extra == "dev"
Requires-Dist: mypy>=0.950; extra == "dev"
Provides-Extra: rpi
Requires-Dist: RPi.GPIO>=0.7.1; extra == "rpi"
Requires-Dist: smbus2>=0.4.1; extra == "rpi"
Requires-Dist: spidev>=3.5; extra == "rpi"
Requires-Dist: pyserial>=3.5; extra == "rpi"
Provides-Extra: all
Requires-Dist: RPi.GPIO>=0.7.1; extra == "all"
Requires-Dist: smbus2>=0.4.1; extra == "all"
Requires-Dist: spidev>=3.5; extra == "all"
Requires-Dist: pyserial>=3.5; extra == "all"
Dynamic: author
Dynamic: author-email
Dynamic: classifier
Dynamic: description
Dynamic: description-content-type
Dynamic: home-page
Dynamic: keywords
Dynamic: license-file
Dynamic: project-url
Dynamic: provides-extra
Dynamic: requires-dist
Dynamic: requires-python
Dynamic: summary
